pyproject_hooks/__init__.py
pyproject_hooks/wrappers.py
pyproject_hooks/in_process/__init__.py
pyproject_hooks/in_process/_in_process.py
pyproject_hooks-0.1.0.dist-info/LICENSE
pyproject_hooks-0.1.0.dist-info/WHEEL
pyproject_hooks-0.1.0.dist-info/METADATA
pyproject_hooks-0.1.0.dist-info/RECORD
