Metadata-Version: 2.1
Name: pyproject-hooks
Version: 0.1.0
Summary: Wrappers to call hooks on pyproject.toml-based build backends.
Author-email: Thomas Kluyver <thomas@kluyver.me.uk>, Pradyun Gedam <mail@pradyunsg.me>
Requires-Python: >=3.7
Classifier: Development Status :: 5 - Production/Stable
Classifier: License :: OSI Approved :: MIT License
Classifier: Intended Audience :: Developers
Classifier: Programming Language :: Python :: 3
Classifier: Operating System :: OS Independent
Requires-Dist: tomli >=1.1.0
Requires-Dist: importlib_metadata;python_version<'3.8'
Requires-Dist: zipp;python_version<'3.8'
